<annotation>
	<folder>Yesterday</folder>
	<filename>f (109).jpg</filename>
	<path>C:/Users/admin/Desktop/Yesterday/f (109).jpg</path>
	<source>
		<database>Unknown</database>
	</source>
	<size>
		<width>2448</width>
		<height>2448</height>
		<depth>3</depth>
	</size>
	<segmented>0</segmented>
	<object>
		<name>embryo</name>
		<pose>Unspecified</pose>
		<truncated>0</truncated>
		<difficult>0</difficult>
		<bndbox>
			<xmin>1309</xmin>
			<ymin>1262</ymin>
			<xmax>1572</xmax>
			<ymax>1572</ymax>
		</bndbox>
	</object>
	<object>
		<name>bloodcell</name>
		<pose>Unspecified</pose>
		<truncated>0</truncated>
		<difficult>0</difficult>
		<bndbox>
			<xmin>847</xmin>
			<ymin>812</ymin>
			<xmax>1272</xmax>
			<ymax>1762</ymax>
		</bndbox>
	</object>
	<object>
		<name>bloodcell</name>
		<pose>Unspecified</pose>
		<truncated>0</truncated>
		<difficult>0</difficult>
		<bndbox>
			<xmin>1393</xmin>
			<ymin>1678</ymin>
			<xmax>1903</xmax>
			<ymax>2031</ymax>
		</bndbox>
	</object>
</annotation>
